centum/__init__.py
centum/delineation.py
centum/irrigation_district.py
centum/plotting.py
centum-0.2.dist-info/LICENSE
centum-0.2.dist-info/METADATA
centum-0.2.dist-info/WHEEL
centum-0.2.dist-info/top_level.txt
centum-0.2.dist-info/RECORD
