Metadata-Version: 2.1
Name: centum
Version: 0.2
Summary: A Python package for water accounting using energy and water balance modeling.
Home-page: https://github.com/yourusername/centum
Author: Your Name
Author-email: your.email@example.com
License: GPL-3.0-or-later  # Use the SPDX identifier
Classifier: Programming Language :: Python :: 3.9
Classifier: Programming Language :: Python :: 3.10
Classifier: Operating System :: OS Independent
Classifier: License :: OSI Approved :: GNU General Public License v3 (GPLv3)
Requires-Python: >=3.9
License-File: LICENSE
